mcp_x_server/__init__.py
mcp_x_server/__main__.py
mcp_x_server/server.py
mcp_x_server/agents/__init__.py
mcp_x_server/agents/tweet_agent.py
mcp_x_server-0.1.5.dist-info/licenses/LICENSE
mcp_x_server-0.1.5.dist-info/METADATA
mcp_x_server-0.1.5.dist-info/WHEEL
mcp_x_server-0.1.5.dist-info/entry_points.txt
mcp_x_server-0.1.5.dist-info/top_level.txt
mcp_x_server-0.1.5.dist-info/RECORD
