Metadata-Version: 2.4
Name: mcp-x-server
Version: 0.1.5
Summary: A mcp x server to post tweets
Home-page: https://github.com/wylu1037/mcp_x_server
Author: wylu1037
Author-email: wylu1037@gmail.com
Requires-Python: >=3.11
License-File: LICENSE
Requires-Dist: fastmcp>=2.2.0
Requires-Dist: python-twitter-v2>=0.9.2
Requires-Dist: dotenv>=0.9.9
Requires-Dist: pydantic-ai>=0.1.2
Requires-Dist: pydantic-ai-slim[duckduckgo,openai]>=0.1.2
Dynamic: author
Dynamic: author-email
Dynamic: home-page
Dynamic: license-file
Dynamic: requires-python
